{
  "tracks": [
    {
      "id": "1761992000277",
      "title": "sad",
      "description": "adada",
      "artist": "Unknown",
      "filename": "1761992000275-57913239.mp3",
      "originalName": "Voicy_Audio Piano.mp3",
      "fileSize": 504872,
      "mimeType": "audio/mpeg",
      "fileUrl": "http://localhost:3002/api/files/1761992000275-57913239.mp3",
      "parentId": null,
      "onChainTrackId": null,
      "voteCount": 1,
      "createdAt": "2025-11-01T10:13:20.277Z"
    },
    {
      "id": "1761992247509",
      "title": "loda",
      "description": "loda",
      "artist": "Unknown",
      "filename": "1761992247508-179246664.mp3",
      "originalName": "Voicy_Audio Piano.mp3",
      "fileSize": 504872,
      "mimeType": "audio/mpeg",
      "fileUrl": "http://localhost:3002/api/files/1761992247508-179246664.mp3",
      "parentId": "1761992000277",
      "onChainTrackId": null,
      "voteCount": 1,
      "createdAt": "2025-11-01T10:17:27.510Z"
    },
    {
      "id": "1761992737445",
      "title": "duad",
      "description": "dada",
      "artist": "Unknown",
      "filename": "1761992737443-369311153.mp3",
      "originalName": "Voicy_Audio Piano.mp3",
      "fileSize": 504872,
      "mimeType": "audio/mpeg",
      "fileUrl": "http://localhost:3002/api/files/1761992737443-369311153.mp3",
      "parentId": "1761992000277",
      "onChainTrackId": null,
      "voteCount": 3,
      "createdAt": "2025-11-01T10:25:37.445Z"
    },
    {
      "id": "1761996409057",
      "title": "byyr",
      "description": "ewur",
      "artist": "Unknown",
      "filename": "1761996409054-602864401.mp3",
      "originalName": "Voicy_Audio Piano.mp3",
      "fileSize": 504872,
      "mimeType": "audio/mpeg",
      "fileUrl": "http://localhost:3002/api/files/1761996409054-602864401.mp3",
      "parentId": null,
      "onChainTrackId": null,
      "voteCount": 0,
      "createdAt": "2025-11-01T11:26:49.057Z"
    },
    {
      "id": "1761999123027",
      "title": "dad",
      "description": "ada",
      "artist": "Unknown",
      "filename": "1761999123025-99894906.mp3",
      "originalName": "Voicy_Audio Piano.mp3",
      "fileSize": 504872,
      "mimeType": "audio/mpeg",
      "fileUrl": "http://localhost:3002/api/files/1761999123025-99894906.mp3",
      "parentId": null,
      "onChainTrackId": null,
      "voteCount": 0,
      "createdAt": "2025-11-01T12:12:03.028Z"
    },
    {
      "id": "1762001164548",
      "title": "The First Ride",
      "description": "sidhu choosewala",
      "artist": "0xD1365e740cB57CF603DE5F91476451b99042E3a5",
      "filename": "1762001164544-681186958.mp3",
      "originalName": "Voicy_Audio Piano.mp3",
      "fileSize": 504872,
      "mimeType": "audio/mpeg",
      "fileUrl": "http://localhost:3002/api/files/1762001164544-681186958.mp3",
      "parentId": null,
      "onChainTrackId": null,
      "voteCount": 0,
      "createdAt": "2025-11-01T12:46:04.548Z"
    }
  ]
}